MANIFEST.in
README.rst
setup.py
pydogs/DOGS_standalone.py
pydogs/__init__.py
pydogs/dogs.py
pydogs/lorenz.py
pydogs/run_opti_IC.py
pydogs/run_uq_tr_test_imperial.py
pydogs/solver_test.py
pydogs/tr.py
pydogs/uq.py
pydogs.egg-info/PKG-INFO
pydogs.egg-info/SOURCES.txt
pydogs.egg-info/dependency_links.txt
pydogs.egg-info/top_level.txt