Metadata-Version: 1.0
Name: pydogs
Version: 0.1.4
Summary: A Delaunay based approach of hyperparmeter optimization
Home-page: https://github.com/deltadogs/pyDOGS4
Author: Shahrouz Ryan Alimo
Author-email: salimoha@ucsd.edu
License: UNKNOWN
Platform: UNKNOWN
